MANIFEST.in
README.md
setup.cfg
setup.py
Vizuka.egg-info/PKG-INFO
Vizuka.egg-info/SOURCES.txt
Vizuka.egg-info/dependency_links.txt
Vizuka.egg-info/entry_points.txt
Vizuka.egg-info/requires.txt
Vizuka.egg-info/top_level.txt
vizuka/__init__.py
vizuka/config.py
vizuka/data_loader.py
vizuka/launch_reduce.py
vizuka/launch_viz.py
vizuka/vizualization.py
vizuka/cluster_viewer/__init__.py
vizuka/cluster_viewer/counter.py
vizuka/cluster_viewer/density.py
vizuka/cluster_viewer/image.py
vizuka/cluster_viewer/plotter.py
vizuka/cluster_viewer/wordcloud.py
vizuka/clustering/__init__.py
vizuka/clustering/clusterizer.py
vizuka/clustering/dbscan.py
vizuka/clustering/grid.py
vizuka/clustering/kMeans.py
vizuka/clustering/loader.py
vizuka/data/cache/.gitkeep
vizuka/data/graph/.gitkeep
vizuka/data/models/.gitkeep
vizuka/data/reduced/.gitkeep
vizuka/data/saved_clusters/.gitkeep
vizuka/data/set/.gitkeep
vizuka/dimension_reduction/__init__.py
vizuka/dimension_reduction/pca.py
vizuka/dimension_reduction/projector.py
vizuka/dimension_reduction/tsne.py
vizuka/example/__init__.py
vizuka/example/load_mnist.py
vizuka/example/tsne#MNIST_example#learning_rate@@1000#n_iter@@12000#perplexity@@50.npz
vizuka/frontier/__init__.py
vizuka/frontier/bhattacharyya.py
vizuka/frontier/deterministic.py
vizuka/frontier/similarity.py
vizuka/graphics/__init__.py
vizuka/graphics/drawing.py
vizuka/graphics/qt_handler.py
vizuka/graphics/qt_helpers.py
vizuka/heatmap/__init__.py
vizuka/heatmap/accuracy.py
vizuka/heatmap/entropy.py
vizuka/heatmap/heatmap.py
vizuka/helpers/__init__.py
vizuka/helpers/ml_helper.py
vizuka/helpers/viz_helper.py
vizuka/plugins/__init__.py
vizuka/plugins/cluster_viewer/How_to_add_cluster_vizualization.py
vizuka/plugins/cluster_viewer/__init__.py
vizuka/plugins/clustering/How_to_add_a_clustering_engine.py
vizuka/plugins/clustering/__init__.py
vizuka/plugins/dimension_reduction/How_to_add_dimension_reduction_plugin.py
vizuka/plugins/dimension_reduction/__init__.py
vizuka/plugins/frontier/How_to_add_new_frontiers_engine.py
vizuka/plugins/frontier/__init__.py
vizuka/plugins/heatmap/How_to_add_heatmap.py
vizuka/plugins/heatmap/__init__.py
vizuka/requirements/requirements.txt