Metadata-Version: 1.0
Name: Vizuka
Version: 0.36.1
Summary: Represents your high-dimensional datas in a 2D space and play with it
Home-page: UNKNOWN
Author: Sofian Medbouhi
Author-email: sof.m.sk@free.fr
License: GPL V3
Platform: UNKNOWN
